.bumpversion.cfg
.virtualenv.dev-requirements.txt
.virtualenv.requirements.txt
LICENSE
MANIFEST.in
Makefile
README.rst
setup.cfg
setup.py
tox.ini
kiwi_obs_plugin/__init__.py
kiwi_obs_plugin/credentials.py
kiwi_obs_plugin/exceptions.py
kiwi_obs_plugin/obs.py
kiwi_obs_plugin/version.py
kiwi_obs_plugin.egg-info/PKG-INFO
kiwi_obs_plugin.egg-info/SOURCES.txt
kiwi_obs_plugin.egg-info/dependency_links.txt
kiwi_obs_plugin.egg-info/entry_points.txt
kiwi_obs_plugin.egg-info/not-zip-safe
kiwi_obs_plugin.egg-info/requires.txt
kiwi_obs_plugin.egg-info/top_level.txt
kiwi_obs_plugin/tasks/__init__.py
kiwi_obs_plugin/tasks/image_obs.py
package/python-kiwi_obs_plugin-rpmlintrc
package/python-kiwi_obs_plugin-spec-template
package/python-kiwi_obs_plugin.changes