Metadata-Version: 2.1
Name: kiwi-obs-plugin
Version: 0.1.4
Summary: KIWI - OBS Plugin
Home-page: https://github.com/OSInside/kiwi-obs-plugin
Author: Marcus Schaefer
Author-email: ms@suse.com
License: GPLv3+
Download-URL: https://download.opensuse.org/repositories/Virtualization:/Appliances:/Builder
Platform: UNKNOWN
Classifier: Development Status :: 5 - Production/Stable
Classifier: Intended Audience :: Developers
Classifier: License :: OSI Approved :: GNU General Public License v3 or later (GPLv3+)
Classifier: Operating System :: POSIX :: Linux
Classifier: Programming Language :: Python :: 3.6
Classifier: Programming Language :: Python :: 3.7
Classifier: Topic :: System :: Operating System
